sci_cases/__init__.py
sci_cases/case_data.py
sci_cases/judgement_details.py
tests/__init__.py
tests/test_case_data.py
sci_cases-0.1.dist-info/LICENSE
sci_cases-0.1.dist-info/METADATA
sci_cases-0.1.dist-info/WHEEL
sci_cases-0.1.dist-info/top_level.txt
sci_cases-0.1.dist-info/RECORD
